dprune/__init__.py
dprune/base.py
dprune/callbacks.py
dprune/pipeline.py
dprune/utils.py
dprune/pruners/__init__.py
dprune/pruners/selection.py
dprune/scorers/__init__.py
dprune/scorers/supervised.py
dprune/scorers/unsupervised.py
dprune-0.0.1.dist-info/licenses/LICENSE
dprune-0.0.1.dist-info/METADATA
dprune-0.0.1.dist-info/WHEEL
dprune-0.0.1.dist-info/top_level.txt
dprune-0.0.1.dist-info/RECORD
