Metadata-Version: 2.4
Name: dprune
Version: 0.0.1
Summary: A lightweight, extensible Python library for data pruning with Hugging Face datasets and transformers
Author-email: Abdul Hameed Azeemi <abdulhameed.azeemi99@gmail.com>
License: MIT License
Project-URL: Homepage, https://github.com/ahazeemi/dPrune
Project-URL: Repository, https://github.com/ahazeemi/dPrune
Project-URL: Issues, https://github.com/ahazeemi/dPrune/issues
Project-URL: Documentation, https://github.com/ahazeemi/dPrune#readme
Keywords: machine-learning,data-pruning,hugging-face,transformers,datasets,nlp,deep-learning
Classifier: Development Status :: 3 - Alpha
Classifier: Intended Audience :: Developers
Classifier: Intended Audience :: Science/Research
Classifier: Operating System :: OS Independent
Classifier: Programming Language :: Python :: 3
Classifier: Programming Language :: Python :: 3.8
Classifier: Programming Language :: Python :: 3.9
Classifier: Programming Language :: Python :: 3.10
Classifier: Programming Language :: Python :: 3.11
Classifier: Programming Language :: Python :: 3.12
Classifier: Topic :: Scientific/Engineering :: Artificial Intelligence
Classifier: Topic :: Software Development :: Libraries :: Python Modules
Classifier: Topic :: Utilities
Requires-Python: >=3.8
License-File: LICENSE
Requires-Dist: torch>=2.0.0
Requires-Dist: transformers>=4.0.0
Requires-Dist: datasets>=2.0.0
Requires-Dist: scikit-learn>=1.0.0
Requires-Dist: tqdm>=4.0.0
Requires-Dist: pandas>=1.0.0
Requires-Dist: accelerate>=0.26.0
Provides-Extra: kenlm
Requires-Dist: kenlm>=0.0.0; extra == "kenlm"
Provides-Extra: test
Requires-Dist: pytest>=7.0.0; extra == "test"
Requires-Dist: pytest-cov>=4.0.0; extra == "test"
Provides-Extra: dev
Requires-Dist: pytest>=7.0.0; extra == "dev"
Requires-Dist: pytest-cov>=4.0.0; extra == "dev"
Requires-Dist: black>=22.0.0; extra == "dev"
Requires-Dist: flake8>=5.0.0; extra == "dev"
Requires-Dist: mypy>=1.0.0; extra == "dev"
Dynamic: license-file
